Metadata-Version: 1.0
Name: viman-probability
Version: 0.1
Summary: Gaussian and Binomial distributions
Home-page: UNKNOWN
Author: Vinoshun Manoratnam
Author-email: UNKNOWN
License: UNKNOWN
Platform: UNKNOWN
